AUTHORS.rst
CONTRIBUTING.rst
HISTORY.rst
LICENSE
MANIFEST.in
README.rst
setup.cfg
setup.py
docs/Makefile
docs/authors.rst
docs/conf.py
docs/contributing.rst
docs/history.rst
docs/index.rst
docs/installation.rst
docs/make.bat
docs/readme.rst
docs/usage.rst
ignore/__init__.py
ignore/cli.py
ignore/ignore.py
ignore_cli.egg-info/PKG-INFO
ignore_cli.egg-info/SOURCES.txt
ignore_cli.egg-info/dependency_links.txt
ignore_cli.egg-info/entry_points.txt
ignore_cli.egg-info/not-zip-safe
ignore_cli.egg-info/requires.txt
ignore_cli.egg-info/top_level.txt
tests/__init__.py
tests/test_ignore.py