Metadata-Version: 1.1
Name: ignore-cli
Version: 0.1.1
Summary: Python package for create .gitignore.
Home-page: https://github.com/petechu/ignore-cli
Author: Phuengton Chummuel
Author-email: phuengton.ch@gmail.com
License: MIT license
Keywords: gitignore ignore
Platform: UNKNOWN
Classifier: Development Status :: 2 - Pre-Alpha
Classifier: Intended Audience :: Developers
Classifier: License :: OSI Approved :: MIT License
Classifier: Natural Language :: English
Classifier: Programming Language :: Python :: 2
Classifier: Programming Language :: Python :: 2.7
Classifier: Programming Language :: Python :: 3
Classifier: Programming Language :: Python :: 3.4
Classifier: Programming Language :: Python :: 3.5
Classifier: Programming Language :: Python :: 3.6
Classifier: Programming Language :: Python :: 3.7
